lightning_app/CHANGELOG.md
lightning_app/MANIFEST.in
lightning_app/README.md
lightning_app/__about__.py
lightning_app/__init__.py
lightning_app/__main__.py
lightning_app/__setup__.py
lightning_app/__version__.py
lightning_app/py.typed
lightning_app/version.info
lightning_app/api/__init__.py
lightning_app/api/http_methods.py
lightning_app/api/request_types.py
lightning_app/cli/__init__.py
lightning_app/cli/cmd_apps.py
lightning_app/cli/cmd_init.py
lightning_app/cli/cmd_install.py
lightning_app/cli/cmd_pl_init.py
lightning_app/cli/cmd_react_ui_init.py
lightning_app/cli/core.py
lightning_app/cli/lightning_cli.py
lightning_app/cli/lightning_cli_delete.py
lightning_app/cli/lightning_cli_launch.py
lightning_app/cli/lightning_cli_list.py
lightning_app/cli/app-template/.gitignore
lightning_app/cli/app-template/LICENSE
lightning_app/cli/app-template/README.md
lightning_app/cli/app-template/app.py
lightning_app/cli/app-template/requirements.txt
lightning_app/cli/app-template/setup.py
lightning_app/cli/app-template/placeholdername/__init__.py
lightning_app/cli/app-template/placeholdername/components/component_a/__init__.py
lightning_app/cli/app-template/placeholdername/components/component_a/component_a.py
lightning_app/cli/app-template/placeholdername/components/component_b/__init__.py
lightning_app/cli/app-template/placeholdername/components/component_b/component_a.py
lightning_app/cli/app-template/tests/README.md
lightning_app/cli/app-template/tests/__init__.py
lightning_app/cli/app-template/tests/requirements.txt
lightning_app/cli/app-template/tests/test_placeholdername_app.py
lightning_app/cli/commands/__init__.py
lightning_app/cli/commands/app_commands.py
lightning_app/cli/commands/cd.py
lightning_app/cli/commands/cp.py
lightning_app/cli/commands/logs.py
lightning_app/cli/commands/ls.py
lightning_app/cli/commands/pwd.py
lightning_app/cli/commands/rm.py
lightning_app/cli/component-template/.gitignore
lightning_app/cli/component-template/LICENSE
lightning_app-2.3.2.dist-info/LICENSE
lightning_app-2.3.2.dist-info/METADATA
lightning_app-2.3.2.dist-info/WHEEL
lightning_app-2.3.2.dist-info/entry_points.txt
lightning_app-2.3.2.dist-info/top_level.txt
lightning_app-2.3.2.dist-info/RECORD
