Metadata-Version: 2.1
Name: lightning-app
Version: 2.3.2
Summary: Use Lightning Apps to build everything from production-ready, multi-cloud ML systems to simple research demos.
Home-page: https://github.com/Lightning-AI/lightning
Author: Lightning-AI et al.
Author-email: name@pytorchlightning.ai
License: Apache-2.0
Download-URL: https://github.com/Lightning-AI/lightning
Project-URL: Bug Tracker, https://github.com/Lightning-AI/lightning/issues
Project-URL: Documentation, https://lightning.ai/lightning-docs
Project-URL: Source Code, https://github.com/Lightning-AI/lightning
Keywords: deep learning,pytorch,AI
Platform: UNKNOWN
Classifier: Environment :: Console
Classifier: Natural Language :: English
Classifier: Development Status :: 4 - Beta
Classifier: Intended Audience :: Developers
Classifier: Topic :: Scientific/Engineering :: Artificial Intelligence
Classifier: Topic :: Scientific/Engineering :: Information Analysis
Classifier: Operating System :: OS Independent
Classifier: Programming Language :: Python :: 3
Classifier: Programming Language :: Python :: 3.8
Classifier: Programming Language :: Python :: 3.9
Classifier: Programming Language :: Python :: 3.10
Classifier: Programming Language :: Python :: 3.11
Requires-Python: >=3.8
License-File: LICENSE
Requires-Dist: lightning-cloud ==0.5.70
Requires-Dist: packaging
Requires-Dist: typing-extensions <5.0,>=4.4.0
Requires-Dist: deepdiff <7.0,>=5.7.0
Requires-Dist: fsspec[http] <2024.0,>=2022.5.0
Requires-Dist: croniter <1.5.0,>=1.3.0
Requires-Dist: traitlets <6.0,>=5.3.0
Requires-Dist: arrow <2.0,>=1.2.0
Requires-Dist: lightning-utilities <1.0,>=0.10.0
Requires-Dist: beautifulsoup4 <5.0,>=4.8.0
Requires-Dist: inquirer <4.0,>=2.10.0
Requires-Dist: psutil <6.0
Requires-Dist: click <9.0
Requires-Dist: python-multipart <1.0,>=0.0.5
Requires-Dist: backoff <3.0,>=2.2.1
Requires-Dist: fastapi <1.0,>=0.92.0
Requires-Dist: starlette
Requires-Dist: pydantic >=1.7.4
Requires-Dist: dateutils <1.0
Requires-Dist: Jinja2 <4.0
Requires-Dist: PyYAML <7.0
Requires-Dist: requests <3.0
Requires-Dist: rich <14.0,>=12.3.0
Requires-Dist: urllib3 <3.0
Requires-Dist: uvicorn <1.0
Requires-Dist: websocket-client <2.0
Requires-Dist: websockets <12.0
Requires-Dist: numpy <2.0,>=1.21.0
Requires-Dist: msgpack
Provides-Extra: all
Requires-Dist: redis <6.0,>=4.0.1 ; extra == 'all'
Requires-Dist: docker <7.0,>=5.0.0 ; extra == 'all'
Requires-Dist: s3fs <2024.0,>=2022.5.0 ; extra == 'all'
Requires-Dist: lightning-api-access >=0.0.3 ; extra == 'all'
Requires-Dist: aiohttp <4.0,>=3.8.0 ; extra == 'all'
Requires-Dist: lightning-fabric >=1.9.0 ; extra == 'all'
Requires-Dist: pytorch-lightning >=1.9.0 ; extra == 'all'
Provides-Extra: cloud
Requires-Dist: redis <6.0,>=4.0.1 ; extra == 'cloud'
Requires-Dist: docker <7.0,>=5.0.0 ; extra == 'cloud'
Requires-Dist: s3fs <2024.0,>=2022.5.0 ; extra == 'cloud'
Provides-Extra: components
Requires-Dist: lightning-api-access >=0.0.3 ; extra == 'components'
Requires-Dist: aiohttp <4.0,>=3.8.0 ; extra == 'components'
Requires-Dist: lightning-fabric >=1.9.0 ; extra == 'components'
Requires-Dist: pytorch-lightning >=1.9.0 ; extra == 'components'
Provides-Extra: dev
Requires-Dist: redis <6.0,>=4.0.1 ; extra == 'dev'
Requires-Dist: docker <7.0,>=5.0.0 ; extra == 'dev'
Requires-Dist: s3fs <2024.0,>=2022.5.0 ; extra == 'dev'
Requires-Dist: lightning-api-access >=0.0.3 ; extra == 'dev'
Requires-Dist: aiohttp <4.0,>=3.8.0 ; extra == 'dev'
Requires-Dist: lightning-fabric >=1.9.0 ; extra == 'dev'
Requires-Dist: pytorch-lightning >=1.9.0 ; extra == 'dev'
Requires-Dist: coverage ==7.3.1 ; extra == 'dev'
Requires-Dist: pytest ==7.4.0 ; extra == 'dev'
Requires-Dist: pytest-timeout ==2.1.0 ; extra == 'dev'
Requires-Dist: pytest-cov ==4.1.0 ; extra == 'dev'
Requires-Dist: pytest-doctestplus ==1.0.0 ; extra == 'dev'
Requires-Dist: pytest-asyncio ==0.21.1 ; extra == 'dev'
Requires-Dist: pytest-rerunfailures ==12.0 ; extra == 'dev'
Requires-Dist: pytest-xdist ==3.3.1 ; extra == 'dev'
Requires-Dist: playwright ==1.38.0 ; extra == 'dev'
Requires-Dist: httpx ==0.25.0 ; extra == 'dev'
Requires-Dist: trio <0.22.0 ; extra == 'dev'
Requires-Dist: pympler ; extra == 'dev'
Requires-Dist: psutil <6.0 ; extra == 'dev'
Requires-Dist: setuptools <69.0 ; extra == 'dev'
Requires-Dist: requests-mock ==1.11.0 ; extra == 'dev'
Requires-Dist: pandas ; extra == 'dev'
Provides-Extra: extra
Requires-Dist: redis <6.0,>=4.0.1 ; extra == 'extra'
Requires-Dist: docker <7.0,>=5.0.0 ; extra == 'extra'
Requires-Dist: s3fs <2024.0,>=2022.5.0 ; extra == 'extra'
Requires-Dist: lightning-api-access >=0.0.3 ; extra == 'extra'
Requires-Dist: aiohttp <4.0,>=3.8.0 ; extra == 'extra'
Requires-Dist: lightning-fabric >=1.9.0 ; extra == 'extra'
Requires-Dist: pytorch-lightning >=1.9.0 ; extra == 'extra'
Provides-Extra: test
Requires-Dist: coverage ==7.3.1 ; extra == 'test'
Requires-Dist: pytest ==7.4.0 ; extra == 'test'
Requires-Dist: pytest-timeout ==2.1.0 ; extra == 'test'
Requires-Dist: pytest-cov ==4.1.0 ; extra == 'test'
Requires-Dist: pytest-doctestplus ==1.0.0 ; extra == 'test'
Requires-Dist: pytest-asyncio ==0.21.1 ; extra == 'test'
Requires-Dist: pytest-rerunfailures ==12.0 ; extra == 'test'
Requires-Dist: pytest-xdist ==3.3.1 ; extra == 'test'
Requires-Dist: playwright ==1.38.0 ; extra == 'test'
Requires-Dist: httpx ==0.25.0 ; extra == 'test'
Requires-Dist: trio <0.22.0 ; extra == 'test'
Requires-Dist: pympler ; extra == 'test'
Requires-Dist: psutil <6.0 ; extra == 'test'
Requires-Dist: setuptools <69.0 ; extra == 'test'
Requires-Dist: requests-mock ==1.11.0 ; extra == 'test'
Requires-Dist: pandas ; extra == 'test'
Provides-Extra: ui
